MANIFEST.in
README.rst
setup.cfg
setup.py
scikit_xray.egg-info/PKG-INFO
scikit_xray.egg-info/SOURCES.txt
scikit_xray.egg-info/dependency_links.txt
scikit_xray.egg-info/top_level.txt
skxray/__init__.py
skxray/calibration.py
skxray/core.py
skxray/diff_roi_choice.py
skxray/dpc.py
skxray/feature.py
skxray/image.py
skxray/recip.py
skxray/spectroscopy.py
skxray/api/__init__.py
skxray/api/diffraction.py
skxray/api/fluorescence.py
skxray/constants/__init__.py
skxray/constants/api.py
skxray/constants/basic.py
skxray/constants/xrf.py
skxray/constants/xrs.py
skxray/constants/data/AtomicConstants.dat
skxray/fitting/__init__.py
skxray/fitting/api.py
skxray/fitting/background.py
skxray/fitting/lineshapes.py
skxray/fitting/models.py
skxray/fitting/base/__init__.py
skxray/fitting/base/parameter_data.py
skxray/io/__init__.py
skxray/io/api.py
skxray/io/avizo_io.py
skxray/io/binary.py
skxray/io/gsas_file_reader.py
skxray/io/net_cdf_io.py
skxray/io/save_powder_output.py
skxray/testing/__init__.py
skxray/testing/decorators.py
skxray/testing/noseclasses.py
src/ctrans.c