Metadata-Version: 1.1
Name: scikit-xray
Version: 0.0.3-r0
Summary: Data analysis tools for X-ray science
Home-page: http://github.com/Nikea/scikit-xray
Author: Brookhaven National Lab
Author-email: UNKNOWN
License: BSD
Keywords: Xray Analysis
Platform: UNKNOWN
Classifier: Development Status :: 3 - Alpha
Classifier: License :: OSI Approved :: BSD License
Classifier: Programming Language :: Python :: 2.7
Classifier: Programming Language :: Python :: 3.4
Classifier: Topic :: Scientific/Engineering :: Physics
Classifier: Topic :: Scientific/Engineering :: Chemistry
Classifier: Topic :: Software Development :: Libraries
Classifier: Intended Audience :: Science/Research
Classifier: Intended Audience :: Developers
Requires: numpy
